backend/__init__.py
backend/utils.py
backend/chat/__init__.py
backend/chat/chat.py
backend/memory/__init__.py
backend/memory/draft.py
backend/memory/research.py
backend/report_type/__init__.py
backend/report_type/basic_report/__init__.py
backend/report_type/basic_report/basic_report.py
backend/report_type/deep_research/__init__.py
backend/report_type/deep_research/example.py
backend/report_type/deep_research/main.py
backend/report_type/detailed_report/__init__.py
backend/report_type/detailed_report/detailed_report.py
backend/server/__init__.py
backend/server/app.py
backend/server/logging_config.py
backend/server/server.py
backend/server/server_utils.py
backend/server/websocket_manager.py
evals/__init__.py
evals/simple_evals/__init__.py
evals/simple_evals/run_eval.py
evals/simple_evals/simpleqa_eval.py
gpt_researcher/__init__.py
gpt_researcher/agent.py
gpt_researcher/prompts.py
gpt_researcher/actions/__init__.py
gpt_researcher/actions/agent_creator.py
gpt_researcher/actions/markdown_processing.py
gpt_researcher/actions/query_processing.py
gpt_researcher/actions/report_generation.py
gpt_researcher/actions/retriever.py
gpt_researcher/actions/utils.py
gpt_researcher/actions/web_scraping.py
gpt_researcher/config/__init__.py
gpt_researcher/config/config.py
gpt_researcher/config/variables/__init__.py
gpt_researcher/config/variables/base.py
gpt_researcher/config/variables/default.py
gpt_researcher/context/__init__.py
gpt_researcher/context/compression.py
gpt_researcher/context/retriever.py
gpt_researcher/document/__init__.py
gpt_researcher/document/azure_document_loader.py
gpt_researcher/document/document.py
gpt_researcher/document/langchain_document.py
gpt_researcher/document/online_document.py
gpt_researcher/llm_provider/__init__.py
gpt_researcher/llm_provider/generic/__init__.py
gpt_researcher/llm_provider/generic/base.py
gpt_researcher/mcp/__init__.py
gpt_researcher/mcp/client.py
gpt_researcher/mcp/research.py
gpt_researcher/mcp/streaming.py
conting_researcher-0.14.0.dist-info/LICENSE
conting_researcher-0.14.0.dist-info/METADATA
conting_researcher-0.14.0.dist-info/WHEEL
conting_researcher-0.14.0.dist-info/top_level.txt
conting_researcher-0.14.0.dist-info/RECORD
